LICENSE.txt
MANIFEST.in
README.md
requirements.txt
setup.cfg
setup.py
artem/__init__.py
artem/artem_core.py
artem/artem_logger.py
artem/artem_pb2.py
artem/artevent.py
artem/cmd.py
artem/commands.py
artem/defaults.py
artem/dialogthread.py
artem/lib.py
artem/others.py
artem/scen_info.py
artem/scenario.py
artem/scselector.py
artem/time_parser.py
artem/version.py
artem.egg-info/PKG-INFO
artem.egg-info/SOURCES.txt
artem.egg-info/dependency_links.txt
artem.egg-info/requires.txt
artem.egg-info/top_level.txt