Metadata-Version: 2.1
Name: artem
Version: 3.0.1
Summary: Chat bot engine for the VK communities
Home-page: https://github.com/Tgjmjgj/artem
Author: Pavel Karpovich
Author-email: Chesh397@mail.ru
License: Apache 2.0
Download-URL: https://github.com/Tgjmjgj/artem/archive/3.0.1.tar.gz
Keywords: vk,chat bot,bot core,bot,bot engine,vk bot
Platform: any
Classifier: License :: OSI Approved :: Apache Software License
Classifier: Development Status :: 3 - Alpha
Classifier: Environment :: Console
Classifier: Intended Audience :: Developers
Classifier: Operating System :: Microsoft :: Windows
Classifier: Operating System :: Unix
Classifier: Programming Language :: Python :: 3 :: Only
Classifier: Programming Language :: Python :: 3.7
Classifier: Topic :: Scientific/Engineering :: Artificial Intelligence
Classifier: Topic :: Communications :: Chat
